MANIFEST.in
README.rst
setup.cfg
setup.py
aspath_graph/__init__.py
aspath_graph/cli.py
aspath_graph/common.py
aspath_graph/junos.py
aspath_graph/transform.py
aspath_graph/utils.py
aspath_graph.egg-info/PKG-INFO
aspath_graph.egg-info/SOURCES.txt
aspath_graph.egg-info/dependency_links.txt
aspath_graph.egg-info/entry_points.txt
aspath_graph.egg-info/requires.txt
aspath_graph.egg-info/top_level.txt
aspath_graph/static/d3.min.js
aspath_graph/static/index.html
aspath_graph/static/netjsongraph-theme.css
aspath_graph/static/netjsongraph.css
aspath_graph/static/netjsongraph.js