Metadata-Version: 1.1
Name: aspath-graph
Version: 1.2
Summary: Take BGP AS PATHs and generate an interactive javascript graph using NetJSON
Home-page: https://github.com/coxley/aspath_graph
Author: Codey Oxley
Author-email: codey.a.oxley+os@gmail.com
License: UNKNOWN
Download-URL: https://github.com/coxley/aspath_graph/tarball/1.1
Keywords: networking,bgp,asn,netjson,json,graph,d3,routes
Platform: UNKNOWN
